{
    "Languages": ["polski", "English"],
    "Places": {
        "English": {
            "Airplane": ["Spy", "1st Class Passenger", "Air Marshal", "Mechanic", "Coach Passenger", "Flight Attendant", "Co-pilot", "Captain"],
            "Bank" : ["Spy", "Armored Car Driver", "Bank Manager", "Loan Consultant", "Bank Robber", "Customer", "Security Guard", "Bank Teller"],
            "Beach": ["Spy", "Beach Bartender", "Kite Surfer", "Lifeguard", "Thief", "Beach Goer", "Beach Photographer", "Ice Cream Man"],
            "Casino": ["Spy", "Bartender", "Head of Security", "Bouncer", "Pit Boss", "Hustler", "Dealer", "Gambler"],
            "Cathedral": ["Spy", "Priest", "Beggar", "Sinner", "Parishioner", "Tourist", "Deacon", "Choir Singer"],
            "Circus Tent": ["Spy", "Acrobat", "Animal Tamer", "Magician", "Audience Member", "Fire Eater", "Clown", "Juggler"],
            "Corporate Party": ["Spy", "Entertainer", "Manager", "Party Crasher", "Owner/CEO", "Admin Assistant", "Accountant", "Delivery Boy"],
            "Crusader Army": ["Spy", "Monk", "Imprisoned Arab", "Servant", "Bishop", "Squire", "Archer", "Knight"],
            "Day Spa": ["Spy", "Customer", "Stylist", "Massage Tech", "Manicurist", "Makeup Artist", "Dematologist", "Beautician"],
            "Embassy": ["Spy", "Security Guard", "Admin Assistant", "Ambassador", "Government Official", "Tourist", "Refugee", "Diplomat"],
            "Hospital": ["Spy", "Nurse", "Doctor", "Anesthesiologist", "Intern", "Patient", "Therapist", "Surgeon"],
            "Hotel": ["Spy", "Doorman", "Security Guard", "Hotel Manager", "Housekeeper", "Hotel Guest", "Bartender", "Valet"],
            "Military Base": ["Spy", "Deserter", "Colonel", "Medic", "Soldier", "Sniper", "XO (Exec. Officer)", "Tank Commander"],
            "Movie Studio": ["Spy", "Stuntman", "Sound Engineer", "Cameraman", "Director", "Costume Artist", "Actor", "Producer"],
            "Ocean Liner": ["Spy", "Rich Passenger", "Cook", "Captain", "Bartender", "Musician", "Waiter", "Ship's Mechanic"],
            "Passenger Train": ["Spy", "Mechanic", "Border Patrol", "Chef", "Engineer", "Steward", "Ticket Taker", "Passenger"],
            "Pirate Ship": ["Spy", "Cook", "Sailor", "Slave", "Cannoneer", "Bound Prisoner", "Cabin Boy", "Pirate Captain"],
            "Polar Station": ["Spy", "Medic", "Geologist", "Expedition Leader", "Biologist", "Radioman", "Hydrologist", "Meteorologist"],
            "Police Station": ["Spy", "Detective", "Lawyer", "Journalist", "Forensic Scientist", "Evidence Archivist", "Patrol Officer", "Ciriminal"],
            "Restaurant": ["Spy", "Musician", "Customer", "Table Busser", "Host", "Head Chef", "Food Critic", "Server"],
            "School": ["Spy", "Gym Teacher", "Student", "Principal", "Security Guard", "Janitor", "Lunch Lady", "Maintenance Man"],
            "Service Station": ["Spy", "Manager", "Tire Specialist", "Motorcyclist", "Car Owner", "Car Washer", "Diagnostic Tech", "Auto Mechanic"],
            "Space Station": ["Spy", "Engineer", "Alien", "Tourist", "Pilot", "Mission Commander", "Scientist", "Doctor"],
            "Submarine": ["Spy", "Cook", "Captian", "Sonar Operator", "Weapons Technician", "Sailor", "Radioman", "Navigator"],
            "Supermarket": ["Spy", "Customer", "Cashier", "Butcher", "Janitor", "Produce Manager", "Food Sample Demo", "Shelf Stocker"],
            "Theater": ["Spy", "Coat Check", "Cue Card Prompter", "Ticket Office Cashier", "Theater Visitor", "Director", "Actor", "Crewman"],
            "University": ["Spy", "Graduate Student", "Professor", "Dean", "Psychologist", "Maintenance Man", "Student", "Advisor"]            
        },
        "polski": {
            "Samolot": ["Szpieg", "Pasażer Pierwszej Klasy", "Pilot Sił Powietrznych", "Mechanik", "Pasażer Autobusu", "Stewardesa", "Drugi Pilot", "Kapitan Samolotu"],
            "Bank": ["Szpieg", "Kierowca Uzbrojonego Samochodu", "Manager Banku", "Konsultant Kredytowy", "Rabuś", "Klient", "Ochroniarz", "Kasjer"],
            "Plaża": ["Szpieg", "Plażowy Barman", "Kitesurfer", "Ratownik", "Złodziej", "Plażowicz", "Plażowy fotograf", "Lodziarz"],
            "Kasyno": ["Szpieg", "Barman", "Szef Bezpieczeństwa", "Wykidajło", "Kierownik Stołów", "Hustler(Cwaniaczek/Człowiek Przedsiębiorczy)", "Krupier", "Hazardzista"],
            "Katedra" : ["Szpieg", "Kapłan", "Żebrak", "Grzesznik", "Parafianin", "Turysta", "Diakon", "Kantor"],
            "Namiot Cyrkowy" : ["Szpieg", "Akrobata", "Oswajacz Zwierząt", "Magik", "Widz", "Połykacz Ognia", "Klaun", "Żongler"],
            "Impreza Korporacyjna" : ["Szpieg", "Komik", "Manager", "Nisczyciel Imprez", "Właściciel Firmy", "Asystent Administratora", "Księgowa", "Chłopiec na Posyłki"],
            "Armia Krzyżowców" : ["Szpieg", "Mnich", "Uwięziony Arab", "Sługa", "Biskup", "Giermek", "Łucznik", "Rycerz"],
            "Spa" : ["Szpieg", "Klient", "Stylista", "Masażystka", "Manikiurzystka", "Wizażystka", "Dematolog", "Kosmetyczka"],
            "Ambasada" : ["Szpieg", "Ochroniarz", "Asystent Administratora", "Ambasador", "Urzędnik Państwowy", "Turysta", "Imigrant", "Dyplomata"],
            "Szpital" : ["Szpieg", "Pielęgniarka", "Doktor", "Anastezjolog", "Stażysta", "Pacjent", "Terapeuta", "Chirurg"],
            "Hotel" : ["Szpieg", "Portier", "Ochroniarz", "Manager", "Dozorca", "Gość", "Barman", "Kamerdyner"],
            "Baza wojskowa" : ["Szpieg", "Dezerter", "Pułkownik", "Medyk", "Żołnierz", "Snajper", "Oficer", "Dowódca Czołgu"],
            "Studio Filmowe" : ["Szpieg", "Kaskader", "Dźwiękowiec", "Kamerzysta", "Reżyser", "Kostiumograf", "Aktor", "Producent"],
            "Statek Międzykontynentalny" : ["Szpieg", "Bogaty Pasażer", "Kucharz", "Kapitan", "Barman", "Muzyk", "Kelnerka", "Mechanik"],
            "Pociąg pasażerki" : ["Szpieg", "Mechanik", "Patrol Graniczny", "Szef Kuchni", "Inżynier", "Steward", "Bileter", "Pasażer"],
            "Statek Piracki" : ["Szpieg", "Kucharz", "Żeglarz", "Niewolnik", "Kanonier", "Związany Więzień", "Kabinowy", "Kapitan Piratów"],
            "Stacja Polarna" : ["Szpieg", "Medyk", "Geolog", "Przywódca Wyprawy", "Biolog", "Operator Radia", "Hydrolog", "Meteorolog"],
            "Komisariat" : ["Szpieg", "Detektyw", "Prawnik", "Dziennikarz", "Biegły Sądowy", "Archiwista dowodów", "Oficer Patrolowy", "Kryminalista"],
            "Restauracja" : ["Szpieg", "Muzyk", "Klient", "Pomocnik Kelnera", "Gospodarz", "Szef Kuchni", "Krytyk Kulinarny", "Kelner"],
            "Szkoła" : ["Szpieg", "Nauczyciel WFu", "Uczeń", "Dyrektor", "Ochroniarz", "Dozorca", "Kucharka", "Konserwator"],
            "Stacja serwisowa" : ["Szpieg", "Manager", "Specjalista od Opon", "Motocyklista", "Właściciel Samochodu", "Pracownik Myjni Samochodowej", "Diagnostyk Samochodowy", "Mechanik Samochodowy"],
            "Stacja Kosmiczna" : ["Szpieg", "Inżynier", "Obcy", "Turysta", "Pilot", "Dowódca Misji", "Naukowiec", "Doktor"],
            "Łódź Podwodna" : ["Szpieg", "Kucharz", "Kapitan", "Operator Sonaru", "Technik Broni", "Marynarz", "Operator Radia", "Nawigator"],
            "Supermarket" : ["Szpieg", "Klient", "Kasjer", "Rzeźnik", "Dozorca", "Manager Produkcji", "Demonstrator Produktów Żywnościowych", "Wykładacz Towaru"],
            "Teatr" : ["Szpieg", "Szatniarka", "Sufler", "Kasjer (biletowy)", "Wizytor", "Reżyser", "Aktor", "Członek Ekipy"],
            "Uniwersytet" : ["Szpieg", "Absolwent", "Profesor", "Dziekan", "Psycholog", "Konserwator", "Student", "Doradca"]
        }
    }
}